pynare/__init__.py
pynare/core.py
pynare/lib.py
pynare-0.1.5.dist-info/METADATA
pynare-0.1.5.dist-info/WHEEL
pynare-0.1.5.dist-info/entry_points.txt
pynare-0.1.5.dist-info/top_level.txt
pynare-0.1.5.dist-info/RECORD
