Metadata-Version: 2.1
Name: pynare
Version: 0.1.5
Summary: run DYNARE from python and access its workspace
Home-page: https://pynare.readthedocs.io/en/latest/index.html
Author: Gregor Boehl
Author-email: admin@gregorboehl.com
License: MIT
Platform: UNKNOWN
Classifier: License :: OSI Approved :: MIT License
Classifier: Programming Language :: Python :: 3
Classifier: Programming Language :: Python :: 3.7
Requires-Dist: numpy
Requires-Dist: pathos
